odoo/addons/ssi_appointment/README.rst
odoo/addons/ssi_appointment/__init__.py
odoo/addons/ssi_appointment/__manifest__.py
odoo/addons/ssi_appointment/menu.xml
odoo/addons/ssi_appointment/controllers/__init__.py
odoo/addons/ssi_appointment/controllers/portal.py
odoo/addons/ssi_appointment/data/approval_template_data.xml
odoo/addons/ssi_appointment/data/ir_sequence_data.xml
odoo/addons/ssi_appointment/data/policy_template_data.xml
odoo/addons/ssi_appointment/data/sequence_template_data.xml
odoo/addons/ssi_appointment/demo/appointment_time_slot_demo.xml
odoo/addons/ssi_appointment/demo/appointment_type_demo.xml
odoo/addons/ssi_appointment/models/__init__.py
odoo/addons/ssi_appointment/models/appointment_schedule.py
odoo/addons/ssi_appointment/models/appointment_time_slot.py
odoo/addons/ssi_appointment/models/appointment_type.py
odoo/addons/ssi_appointment/models/res_users.py
odoo/addons/ssi_appointment/security/ir.model.access.csv
odoo/addons/ssi_appointment/security/ir_module_category_data.xml
odoo/addons/ssi_appointment/security/res_group_data.xml
odoo/addons/ssi_appointment/static/description/icon.png
odoo/addons/ssi_appointment/views/appointment_schedule_portal_templates.xml
odoo/addons/ssi_appointment/views/appointment_schedule_views.xml
odoo/addons/ssi_appointment/views/appointment_time_slot_views.xml
odoo/addons/ssi_appointment/views/appointment_type_views.xml
odoo14_addon_ssi_appointment-14.0.1.7.0.dist-info/METADATA
odoo14_addon_ssi_appointment-14.0.1.7.0.dist-info/WHEEL
odoo14_addon_ssi_appointment-14.0.1.7.0.dist-info/top_level.txt
odoo14_addon_ssi_appointment-14.0.1.7.0.dist-info/RECORD
